MANIFEST.in
README.rst
setup.py
ckanext/__init__.py
ckanext-esdstandards-data/__init__.py
ckanext-esdstandards-data/functions.csv
ckanext-esdstandards-data/services.csv
ckanext/esdstandards/__init__.py
ckanext/esdstandards/commands.py
ckanext/esdstandards/helpers.py
ckanext/esdstandards/logic.py
ckanext/esdstandards/model.py
ckanext/esdstandards/plugin.py
ckanext/esdstandards/validators.py
ckanext/esdstandards/fanstatic/autocomplete.js
ckanext/esdstandards/fanstatic/resource.config
ckanext/esdstandards/templates/snippets/esd_functions.html
ckanext/esdstandards/templates/snippets/esd_functions_additional_info.html
ckanext/esdstandards/templates/snippets/esd_services.html
ckanext/esdstandards/templates/snippets/esd_services_additional_info.html
ckanext/esdstandards/tests/__init__.py
ckanext/esdstandards/tests/plugin.py
ckanext/esdstandards/tests/test_commands.py
ckanext/esdstandards/tests/test_functional.py
ckanext/esdstandards/tests/test_helpers.py
ckanext/esdstandards/tests/test_logic.py
ckanext/esdstandards/tests/test_validators.py
ckanext/esdstandards/tests/mockplugin/__init__.py
ckanext/esdstandards/tests/mockplugin/plugin.py
ckanext/esdstandards/tests/mockplugin/templates/package/snippets/package_basic_fields.html
ckanext_esdstandards.egg-info/PKG-INFO
ckanext_esdstandards.egg-info/SOURCES.txt
ckanext_esdstandards.egg-info/dependency_links.txt
ckanext_esdstandards.egg-info/entry_points.txt
ckanext_esdstandards.egg-info/namespace_packages.txt
ckanext_esdstandards.egg-info/not-zip-safe
ckanext_esdstandards.egg-info/top_level.txt