Metadata-Version: 1.0
Name: ckanext-esdstandards
Version: 0.0.5
Summary: Helpers for working with LGA's ESD standards on CKAN
Home-page: https://github.com/okfn/ckanext-esdstandards
Author: Open Knowledge
Author-email: services@okfn.org
License: AGPL
Platform: UNKNOWN
